factorytest/__init__.py
factorytest/__main__.py
factorytest/anx.py
factorytest/audio.py
factorytest/camera.py
factorytest/factorytest.glade
factorytest/gpio.py
factorytest/led.py
factorytest/modem.py
factorytest/motor.py
factorytest/selftest.py
factorytest/bmap/__init__.py
factorytest/bmap/bmapcopy.py
factorytest/bmap/helpers.py
factorytest/ioctl/ff_structure.py
factorytest/ioctl/input.py
factorytest/ioctl/ioctl.py
factorytest_pinephone-0.47.0.dist-info/METADATA
factorytest_pinephone-0.47.0.dist-info/WHEEL
factorytest_pinephone-0.47.0.dist-info/entry_points.txt
factorytest_pinephone-0.47.0.dist-info/top_level.txt
factorytest_pinephone-0.47.0.dist-info/zip-safe
factorytest_pinephone-0.47.0.dist-info/RECORD
